convertable_key_model/__init__.py
convertable_key_model/convertable_key_model.py
test/__init__.py
test/test.py
convertable_key_model-1.0.3.dist-info/METADATA
convertable_key_model-1.0.3.dist-info/WHEEL
convertable_key_model-1.0.3.dist-info/top_level.txt
convertable_key_model-1.0.3.dist-info/RECORD
