Metadata-Version: 2.1
Name: convertable-key-model
Version: 1.0.3
Summary: ConvertableKeyModel: Dynamic key conversion for Pydantic models
Home-page: https://github.com/jogakdal/standard-api-response
Author: 황용호
Author-email: jogakdal@gmail.com
Keywords: jogakdal,standard,API,response,helper,pydantic,convert,key
Classifier: Programming Language :: Python :: 3
Classifier: Operating System :: OS Independent
Requires-Python: >=3.6
Requires-Dist: pydantic
Requires-Dist: fastapi
Requires-Dist: inflection
Requires-Dist: advanced-python-singleton
